sram_model.v
/*
 * Module: sram_model
 * Description:
 * A behavioral model for a simple synchronous SRAM chip. It includes a reset
 * and has correctly named ports to interface with the controller and testbench.
 * This is the stable, working version for the SRAM-only project.
 */
module sram_model #(
    parameter DATA_WIDTH = 16,
    parameter ADDR_WIDTH = 8
)(
    input                       clk,
    input                       rst_n,
    inout  [DATA_WIDTH-1:0]     sram_data_io,
    input  [ADDR_WIDTH-1:0]     sram_addr_i,
    input                       sram_ce_i,
    input                       sram_we_i,
    input                       sram_oe_i
);

    // Internal memory array
    reg [DATA_WIDTH-1:0] memory [0:(1<<ADDR_WIDTH)-1];
    
    // On the positive clock edge, perform writes
    always @(posedge clk or negedge rst_n) begin
        if (!rst_n) begin
            // On reset, do nothing to the memory contents.
        end else begin
            if (sram_ce_i && sram_we_i && !sram_oe_i) begin
                memory[sram_addr_i] <= sram_data_io;
            end
        end
    end

    // Combinational logic to drive the data bus during a read
    assign sram_data_io = (sram_ce_i && !sram_we_i && sram_oe_i) ? memory[sram_addr_i] : {DATA_WIDTH{1'bz}};

endmodule

sram_controller.v
/*
 * Module: sram_controller
 * Description:
 * A robust, synchronous SRAM controller. It uses a multi-state Finite State
 * Machine (FSM) to handle read and write requests, ensuring correct timing
 * and stable data output. This is the fully debugged, working version.
 */
module sram_controller #(
    parameter ADDR_WIDTH = 8,
    parameter DATA_WIDTH = 16
)(
    // Processor-side Interface
    input                       clk,
    input                       rst_n,
    input                       req_i,
    input                       wr_en_i,
    input      [ADDR_WIDTH-1:0] addr_i,
    input      [DATA_WIDTH-1:0] wdata_i,
    output reg                  ack_o,
    output reg [DATA_WIDTH-1:0] rdata_o,

    // SRAM-side Interface
    output reg [ADDR_WIDTH-1:0] sram_addr_o,
    inout      [DATA_WIDTH-1:0] sram_data_io,
    output reg                  sram_ce_o,
    output reg                  sram_we_o,
    output reg                  sram_oe_o
);

    // FSM State Definitions
    localparam IDLE           = 3'b001;
    localparam WRITE          = 3'b010;
    localparam READ_SETUP     = 3'b011;
    localparam READ_CAPTURE   = 3'b100;
    localparam READ_ACK       = 3'b101;
    
    reg [2:0] current_state, next_state;

    // Internal registers to hold request info
    reg [ADDR_WIDTH-1:0] addr_reg;
    reg [DATA_WIDTH-1:0] wdata_reg;

    // Sequential Logic Block (State transitions and data latching)
    always @(posedge clk or negedge rst_n) begin
        if (!rst_n) begin
            current_state <= IDLE;
            rdata_o <= 0;
        end else begin
            current_state <= next_state;
            
            // Latch inputs when a new request arrives
            if (current_state == IDLE && req_i) begin
                addr_reg <= addr_i;
                wdata_reg <= wdata_i;
            end

            // Capture data from SRAM at the end of the CAPTURE state
            if (current_state == READ_CAPTURE) begin
                rdata_o <= sram_data_io;
            end
        end
    end

    // Combinational Logic Block (State-based outputs and next state logic)
    always @(*) begin
        // Default values for signals
        next_state   = current_state;
        ack_o        = 1'b0;
        sram_addr_o  = addr_reg;
        sram_ce_o    = 1'b0;
        sram_we_o    = 1'b0;
        sram_oe_o    = 1'b0;
        
        case (current_state)
            IDLE: begin
                if (req_i) begin
                    if (wr_en_i) begin
                        next_state = WRITE;
                    end else begin
                        next_state = READ_SETUP;
                    end
                end
            end
            
            WRITE: begin
                sram_ce_o = 1'b1;
                sram_we_o = 1'b1;
                ack_o = 1'b1;
                next_state = IDLE;
            end
            
            READ_SETUP: begin
                sram_ce_o = 1'b1;
                sram_oe_o = 1'b1;
                next_state = READ_CAPTURE;
            end

            READ_CAPTURE: begin
                sram_ce_o = 1'b1;
                sram_oe_o = 1'b1;
                next_state = READ_ACK;
            end
            
            READ_ACK: begin
                ack_o = 1'b1;
                next_state = IDLE;
            end
            
            default: begin
                next_state = IDLE;
            end
        endcase
    end
    
    // Drive data to SRAM only during a write operation
    assign sram_data_io = (current_state == WRITE) ? wdata_reg : {DATA_WIDTH{1'bz}};

endmodule

tb_sram_controller.v
/*
 * Module: tb_sram_controller
 * Description:
 * A simple, effective testbench for the sram_controller. It writes two
 * values to the SRAM model via the controller and then reads them back
 * to verify the data integrity. This is the stable, working version for
 * the SRAM-only project.
 */
`timescale 1ns/1ps

module tb_sram_controller;

    // Parameters
    localparam ADDR_WIDTH = 8;
    localparam DATA_WIDTH = 16;
    localparam CLK_PERIOD = 10;

    // Testbench signals
    reg clk;
    reg rst_n;
    reg req_i;
    reg wr_en_i;
    reg [ADDR_WIDTH-1:0] addr_i;
    reg [DATA_WIDTH-1:0] wdata_i;
    wire ack_o;
    wire [DATA_WIDTH-1:0] rdata_o;

    // Wires to connect controller to model
    wire [ADDR_WIDTH-1:0] sram_addr;
    wire [DATA_WIDTH-1:0] sram_data;
    wire sram_ce, sram_we, sram_oe;
    
    // Instantiate the Controller (DUT)
    sram_controller #(
        .ADDR_WIDTH(ADDR_WIDTH),
        .DATA_WIDTH(DATA_WIDTH)
    ) dut (
        .clk(clk), .rst_n(rst_n), .req_i(req_i), .wr_en_i(wr_en_i), .addr_i(addr_i),
        .wdata_i(wdata_i), .ack_o(ack_o), .rdata_o(rdata_o),
        .sram_addr_o(sram_addr), .sram_data_io(sram_data), .sram_ce_o(sram_ce),
        .sram_we_o(sram_we), .sram_oe_o(sram_oe)
    );

    // Instantiate the SRAM Model
    sram_model #(
        .ADDR_WIDTH(ADDR_WIDTH),
        .DATA_WIDTH(DATA_WIDTH)
    ) sram_inst (
        .clk(clk), .rst_n(rst_n), .sram_addr_i(sram_addr), .sram_data_io(sram_data),
        .sram_ce_i(sram_ce), .sram_we_i(sram_we), .sram_oe_i(sram_oe)
    );

    // Clock generation
    initial begin
        clk = 0;
        forever #(CLK_PERIOD/2) clk = ~clk;
    end

    // Test Sequence
    initial begin
        $dumpfile("sram_controller_waves.vcd");
        $dumpvars(0, tb_sram_controller);
        
        rst_n = 0;
        req_i = 0;
        #20;
        rst_n = 1;
        #40;

        $display("----------------------------------------");
        $display("Starting Simulation...");
        
        write_mem(8'h10, 16'hFACE);
        write_mem(8'hA5, 16'hBEEF);

        read_mem(8'h10, 16'hFACE);
        read_mem(8'hA5, 16'hBEEF);

        $display("----------------------------------------");
        $display("Simulation Finished.");
        $finish;
    end

    // Helper task for writing to memory
    task write_mem(input [ADDR_WIDTH-1:0] address, input [DATA_WIDTH-1:0] data);
        begin
            $display("[%0t] >> Writing 0x%h to address 0x%h", $time, data, address);
            @(posedge clk);
            req_i <= 1;
            wr_en_i <= 1;
            addr_i <= address;
            wdata_i <= data;
            @(posedge clk);
            while(!ack_o) @(posedge clk);
            req_i <= 0;
            $display("[%0t] << Controller acknowledged the write request.", $time);
        end
    endtask

    // Helper task for reading from memory
    task read_mem(input [ADDR_WIDTH-1:0] address, input [DATA_WIDTH-1:0] expected_data);
        begin
            $display("[%0t] >> Reading from address 0x%h", $time, address);
            @(posedge clk);
            req_i <= 1;
            wr_en_i <= 0;
            addr_i <= address;
            @(posedge clk);
            while(!ack_o) @(posedge clk);
            if (rdata_o == expected_data)
                $display("[%0t] << Read data: 0x%h (Correct!)", $time, rdata_o);
            else
                $display("[%0t] << Read data: 0x%h (ERROR! Expected: 0x%h)", $time, rdata_o, expected_data);
            req_i <= 0;
        end
    endtask

endmodule

sram_controller_waves.vcd
$date
	Sun Aug 31 12:26:37 2025
$end
$version
	Icarus Verilog
$end
$timescale
	1ps
$end
$scope module tb_sram_controller $end
$var wire 1 ! ack_o $end
$var wire 16 " rdata_o [15:0] $end
$var wire 8 # sram_addr [7:0] $end
$var wire 1 $ sram_ce $end
$var wire 16 % sram_data [15:0] $end
$var wire 1 & sram_oe $end
$var wire 1 ' sram_we $end
$var reg 8 ( addr_i [7:0] $end
$var reg 1 ) clk $end
$var reg 1 * req_i $end
$var reg 1 + rst_n $end
$var reg 16 , wdata_i [15:0] $end
$var reg 1 - wr_en_i $end
$scope module dut $end
$var wire 8 . addr_i [7:0] $end
$var wire 1 / clk $end
$var wire 1 0 req_i $end
$var wire 1 1 rst_n $end
$var wire 16 2 sram_data_io [15:0] $end
$var wire 16 3 wdata_i [15:0] $end
$var wire 1 4 wr_en_i $end
$var reg 1 5 ack_o $end
$var reg 8 6 addr_reg [7:0] $end
$var reg 3 7 current_state [2:0] $end
$var reg 3 8 next_state [2:0] $end
$var reg 16 9 rdata_o [15:0] $end
$var reg 8 : sram_addr_o [7:0] $end
$var reg 1 ; sram_ce_o $end
$var reg 1 < sram_oe_o $end
$var reg 1 = sram_we_o $end
$var reg 16 > wdata_reg [15:0] $end
$upscope $end
$scope module sram_inst $end
$var wire 1 / clk $end
$var wire 1 1 rst_n $end
$var wire 8 ? sram_addr_i [7:0] $end
$var wire 1 $ sram_ce_i $end
$var wire 16 @ sram_data_io [15:0] $end
$var wire 1 & sram_oe_i $end
$var wire 1 ' sram_we_i $end
$upscope $end
$scope task read_mem $end
$var reg 8 A address [7:0] $end
$var reg 16 B expected_data [15:0] $end
$upscope $end
$scope task write_mem $end
$var reg 8 C address [7:0] $end
$var reg 16 D data [15:0] $end
$upscope $end
$upscope $end
$enddefinitions $end
#0
$dumpvars
bx D
bx C
bx B
bx A
bz @
bx ?
bx >
0=
0<
0;
bx :
b0 9
b1 8
b1 7
bx 6
05
x4
bx 3
bz 2
01
00
0/
bx .
x-
bx ,
0+
0*
0)
bx (
0'
0&
bz %
0$
bx #
b0 "
0!
$end
#5000
1)
1/
#10000
0)
0/
#15000
1)
1/
#20000
0)
0/
1+
11
#25000
1)
1/
#30000
0)
0/
#35000
1)
1/
#40000
0)
0/
#45000
1)
1/
#50000
0)
0/
#55000
1)
1/
#60000
0)
0/
b1111101011001110 D
b10000 C
#65000
b10 8
b1111101011001110 ,
b1111101011001110 3
b10000 (
b10000 .
1-
14
1*
10
1)
1/
#70000
0)
0/
#75000
b1 8
15
1!
1=
1'
1;
1$
b10000 :
b10000 #
b10000 ?
b1111101011001110 %
b1111101011001110 2
b1111101011001110 @
b1111101011001110 >
b10000 6
b10 7
1)
1/
#80000
0)
0/
#85000
bz %
bz 2
bz @
0=
0'
0;
0$
05
0!
b1 7
0*
00
b1011111011101111 D
b10100101 C
1)
1/
#90000
0)
0/
#95000
b10 8
b1011111011101111 ,
b1011111011101111 3
b10100101 (
b10100101 .
1*
10
1)
1/
#100000
0)
0/
#105000
b1 8
15
1!
1=
1'
1;
1$
b10100101 :
b10100101 #
b10100101 ?
b1011111011101111 %
b1011111011101111 2
b1011111011101111 @
b1011111011101111 >
b10100101 6
b10 7
1)
1/
#110000
0)
0/
#115000
bz %
bz 2
bz @
0=
0'
0;
0$
05
0!
b1 7
0*
00
b1111101011001110 B
b10000 A
1)
1/
#120000
0)
0/
#125000
b11 8
b10000 (
b10000 .
0-
04
1*
10
1)
1/
#130000
0)
0/
#135000
b1111101011001110 %
b1111101011001110 2
b1111101011001110 @
b100 8
1<
1&
1;
1$
b10000 :
b10000 #
b10000 ?
b10000 6
b11 7
1)
1/
#140000
0)
0/
#145000
b101 8
1<
1&
1;
1$
b100 7
1)
1/
#150000
0)
0/
#155000
bz %
bz 2
bz @
b1 8
15
1!
0<
0&
0;
0$
b1111101011001110 9
b1111101011001110 "
b101 7
1)
1/
#160000
0)
0/
#165000
05
0!
b1 7
0*
00
b1011111011101111 B
b10100101 A
1)
1/
#170000
0)
0/
#175000
b11 8
b10100101 (
b10100101 .
1*
10
1)
1/
#180000
0)
0/
#185000
b1011111011101111 %
b1011111011101111 2
b1011111011101111 @
b100 8
1<
1&
1;
1$
b10100101 :
b10100101 #
b10100101 ?
b10100101 6
b11 7
1)
1/
#190000
0)
0/
#195000
b101 8
1<
1&
1;
1$
b100 7
1)
1/
#200000
0)
0/
#205000
bz %
bz 2
bz @
b1 8
15
1!
0<
0&
0;
0$
b1011111011101111 9
b1011111011101111 "
b101 7
1)
1/
#210000
0)
0/
#215000
05
0!
b1 7
0*
00
1)
1/
