sram_model.v
/*

 * Module: sram_model

 * Description:

 * A behavioral model for a simple synchronous SRAM chip. It includes a reset

 * and has correctly named ports to interface with the controller and testbench.

 * This is the stable, working version for the SRAM-only project.

 */

module sram_model #(

  parameter DATA_WIDTH = 16,

  parameter ADDR_WIDTH = 8

)(

  input            clk,

  input            rst_n,

  inout [DATA_WIDTH-1:0]   sram_data_io,

  input [ADDR_WIDTH-1:0]   sram_addr_i,

  input            sram_ce_i,

  input            sram_we_i,

  input            sram_oe_i

);



  // Internal memory array

  reg [DATA_WIDTH-1:0] memory [0:(1<<ADDR_WIDTH)-1];

   

  // On the positive clock edge, perform writes

  always @(posedge clk or negedge rst_n) begin

    if (!rst_n) begin

      // On reset, do nothing to the memory contents.

    end else begin

      if (sram_ce_i && sram_we_i && !sram_oe_i) begin

        memory[sram_addr_i] <= sram_data_io;

      end

    end

  end



  // Combinational logic to drive the data bus during a read

  assign sram_data_io = (sram_ce_i && !sram_we_i && sram_oe_i) ? memory[sram_addr_i] : {DATA_WIDTH{1'bz}};



endmodule

sram_controller.v
/*

 * Module: sram_controller (Pipelined Version)

 * Description:

 * A two-stage pipelined SRAM controller to improve throughput.

 * Stage 1 (Command): Latches incoming requests.

 * Stage 2 (Execution): Executes the SRAM read/write operation.

 * A valid/ready handshake connects the two stages.

 */

module sram_controller #(

  parameter ADDR_WIDTH = 8,

  parameter DATA_WIDTH = 16

)(

  // Processor-side Interface (on proc_clk)

  input            proc_clk,

  input            req_i,

  input            wr_en_i,

  input   [ADDR_WIDTH-1:0] addr_i,

  input   [DATA_WIDTH-1:0] wdata_i,

  output           ack_o,



  // SRAM-side Interface (on sram_clk)

  input            sram_clk,

  input            rst_n,

  output reg [DATA_WIDTH-1:0] rdata_o,

  output   [ADDR_WIDTH-1:0] sram_addr_o, // Now driven by pipeline reg

  inout   [DATA_WIDTH-1:0] sram_data_io,

  output reg         sram_ce_o,

  output reg         sram_we_o,

  output reg         sram_oe_o

);



  // FSM states for the Execution Stage (Stage 2)

  localparam EXEC_IDLE=4'b0001, EXEC_DECODE=4'b0010, EXEC_WRITE=4'b0100, EXEC_READ_SETUP=4'b1000, EXEC_READ_CAPTURE=4'b1001;

  reg [3:0] exec_current_state, exec_next_state;



  // Internal register for acknowledgement

  reg ack_internal;



  // --- CDC Logic (Unchanged) ---

  // Synchronize the request signal (proc_clk -> sram_clk)

  reg req_s1, req_s2, req_s3;

  always @(posedge sram_clk or negedge rst_n) begin

    if (!rst_n) {req_s1, req_s2, req_s3} <= 3'b0;

    else    {req_s1, req_s2, req_s3} <= {req_i, req_s1, req_s2};

  end

  wire req_event = req_s2 & ~req_s3;



  // Synchronize the ack signal back (sram_clk -> proc_clk)

  reg ack_p1, ack_p2;

  always @(posedge proc_clk or negedge rst_n) begin

    if (!rst_n) {ack_p1, ack_p2} <= 2'b0;

    else    {ack_p1, ack_p2} <= {ack_internal, ack_p1};

  end

  assign ack_o = ack_p2;



  // --- Pipeline Handshake and Registers ---

  // Pipeline Register between Stage 1 and Stage 2

  reg cmd_valid_reg;

  reg [ADDR_WIDTH-1:0] cmd_addr_reg;

  reg [DATA_WIDTH-1:0] cmd_wdata_reg;

  reg cmd_wr_en_reg;



  // Handshake Control Signals

  wire exec_ready; // Is the Execution Stage ready for a new command?

  wire cmd_fire;  // Signal to transfer command from Stage 1 to Stage 2



  // --- Stage 1: Command Stage ---

  // Latches a new request from the processor domain.

  always @(posedge sram_clk or negedge rst_n) begin

    if (!rst_n) begin

      cmd_valid_reg <= 1'b0;

    end else begin

      // If Stage 2 accepts the command, the pipeline register becomes free

      if (cmd_fire) begin

        cmd_valid_reg <= 1'b0;

      end

      // A new request arrives, latch it if the pipeline register is free.

      // If not free, the request is effectively stalled (req_event will be ignored

      // in subsequent cycles until the pipeline is free).

      if (req_event && !cmd_valid_reg) begin

        cmd_addr_reg <= addr_i;

        cmd_wdata_reg <= wdata_i;

        cmd_wr_en_reg <= wr_en_i;

        cmd_valid_reg <= 1'b1;

      end

    end

  end

   

  // --- Stage 2: Execution Stage ---

  // Executes the SRAM transaction.

  assign exec_ready = (exec_current_state == EXEC_IDLE);

  assign cmd_fire = cmd_valid_reg && exec_ready;



  // Execution FSM Sequential Logic (runs on sram_clk)

  always @(posedge sram_clk or negedge rst_n) begin

    if (!rst_n) begin

      exec_current_state <= EXEC_IDLE;

      rdata_o      <= 0;

    end else begin

      exec_current_state <= exec_next_state;

      if (exec_current_state == EXEC_READ_CAPTURE) begin

        rdata_o <= sram_data_io;

      end

    end

  end



  // Execution FSM Combinational Logic (runs on sram_clk)

  always @(*) begin

    exec_next_state = exec_current_state;

    ack_internal  = 1'b0;

    sram_ce_o    = 1'b0;

    sram_we_o    = 1'b0;

    sram_oe_o    = 1'b0;



    case (exec_current_state)

      EXEC_IDLE: begin

        if (cmd_fire) begin // Start a new transaction

          exec_next_state = cmd_wr_en_reg ? EXEC_WRITE : EXEC_READ_SETUP;

        end

      end

      EXEC_WRITE: begin

        sram_ce_o  = 1'b1;

        sram_we_o  = 1'b1;

        ack_internal = 1'b1;

        exec_next_state  = EXEC_IDLE; // Done, go back to idle

      end

      EXEC_READ_SETUP: begin

        sram_ce_o = 1'b1;

        sram_oe_o = 1'b1;

        exec_next_state = EXEC_READ_CAPTURE;

      end

      EXEC_READ_CAPTURE: begin

        sram_ce_o  = 1'b1;

        sram_oe_o  = 1'b1;

        ack_internal = 1'b1;

        exec_next_state  = EXEC_IDLE; // Done, go back to idle

      end

      default: exec_next_state = EXEC_IDLE;

    endcase

  end



  // --- Data Path Assignments ---

  assign sram_addr_o = cmd_addr_reg;

  assign sram_data_io = (exec_current_state == EXEC_WRITE) ? cmd_wdata_reg : {DATA_WIDTH{1'bz}};



endmodule

tb_sram_controller.v
/*

 * Module: tb_sram_controller (Final, Pipelined Test Version)

 * Description:

 * A testbench for the sram_controller. This version includes a corrected

 * test case that issues wide, back-to-back request pulses to verify 

 * the pipeline's functionality and avoid CDC pulse-width issues.

 */

`timescale 1ns/1ps



module tb_sram_controller;



  // Parameters and signals

  localparam ADDR_WIDTH = 8;

  localparam DATA_WIDTH = 16;

  localparam SRAM_CLK_PERIOD = 10;

  localparam PROC_CLK_PERIOD = 7;

  reg sram_clk, proc_clk, rst_n, req_i, wr_en_i;

  reg [ADDR_WIDTH-1:0] addr_i;

  reg [DATA_WIDTH-1:0] wdata_i;

  wire ack_o;

  wire [DATA_WIDTH-1:0] rdata_o;

  wire [ADDR_WIDTH-1:0] sram_addr;

  wire [DATA_WIDTH-1:0] sram_data;

  wire sram_ce, sram_we, sram_oe;



  // Instantiations

  sram_controller #(.ADDR_WIDTH(ADDR_WIDTH), .DATA_WIDTH(DATA_WIDTH)) dut (

    .proc_clk(proc_clk), .sram_clk(sram_clk), .rst_n(rst_n),

    .req_i(req_i), .wr_en_i(wr_en_i), .addr_i(addr_i), .wdata_i(wdata_i),

    .ack_o(ack_o), .rdata_o(rdata_o), .sram_addr_o(sram_addr),

    .sram_data_io(sram_data), .sram_ce_o(sram_ce), .sram_we_o(sram_we),

    .sram_oe_o(sram_oe)

  );



  sram_model #(.ADDR_WIDTH(ADDR_WIDTH), .DATA_WIDTH(DATA_WIDTH)) sram_inst (

    .clk(sram_clk), .rst_n(rst_n), .sram_addr_i(sram_addr),

    .sram_data_io(sram_data), .sram_ce_i(sram_ce), .sram_we_i(sram_we),

    .sram_oe_i(sram_oe)

  );



  // Clocks

  initial begin

    sram_clk = 0;

    forever #(SRAM_CLK_PERIOD/2) sram_clk = ~sram_clk;

  end



  initial begin

    proc_clk = 0;

    forever #(PROC_CLK_PERIOD/2) proc_clk = ~proc_clk;

  end



  // Test Sequence (Corrected for Pulse Width)

  initial begin

    $dumpfile("sram_controller_cdc_waves.vcd");

    $dumpvars(0, tb_sram_controller);

    rst_n = 0;

    req_i = 0;

    #20;

    rst_n = 1;

    #40;



    $display("----------------------------------------");

    $display("Starting FINAL Pipelined Simulation (Wide Pulse)...");



    // Step 1: Pre-load memory

    write_mem(8'hA5, 16'hBEEF);

     

    // Step 2: Issue two separate, wide requests

    $display("[%0t] >> Issuing a wide Write pulse then a wide Read pulse.", $time);

     

    // Issue first request (Write) - hold req_i for 3 proc_clk cycles

    @(posedge proc_clk);

    req_i <= 1; wr_en_i <= 1; addr_i <= 8'h10; wdata_i <= 16'hFACE;

    @(posedge proc_clk);

    @(posedge proc_clk);

    @(posedge proc_clk);

    req_i <= 0;

     

    // Add a small gap between requests for clarity in the waveform

    @(posedge proc_clk);



    // Issue second request (Read) - hold req_i for 3 proc_clk cycles

    @(posedge proc_clk);

    req_i <= 1; wr_en_i <= 0; addr_i <= 8'hA5;

    @(posedge proc_clk);

    @(posedge proc_clk);

    @(posedge proc_clk);

    req_i <= 0;

     

    // Wait for pipelined operations to finish

    #200;



    // Step 3: Verify the results

    $display("[%0t] >> Verifying the results of the pipelined sequence.", $time);

    read_mem(8'h10, 16'hFACE);

    read_mem(8'hA5, 16'hBEEF);

     

    $display("----------------------------------------");

    $display("Simulation Finished.");

    $finish;

  end



  // Write task

  task write_mem(input [ADDR_WIDTH-1:0] address, input [DATA_WIDTH-1:0] data);

    begin

      $display("[%0t] >> Writing 0x%h to address 0x%h", $time, data, address);

      @(posedge proc_clk);

      req_i <= 1; wr_en_i <= 1; addr_i <= address; wdata_i <= data;

      while(!ack_o) @(posedge proc_clk);

      req_i <= 0;

      $display("[%0t] << Controller acknowledged the write request.", $time);

      @(posedge proc_clk);

    end

  endtask



  // Read task

  task read_mem(input [ADDR_WIDTH-1:0] address, input [DATA_WIDTH-1:0] expected_data);

    begin

      $display("[%0t] >> Reading from address 0x%h", $time, address);

      @(posedge proc_clk);

      req_i <= 1; wr_en_i <= 0; addr_i <= address;

      while(!ack_o) @(posedge proc_clk);

      req_i <= 0;

      @(posedge proc_clk);

      if (rdata_o == expected_data)

        $display("[%0t] << Read data: 0x%h (Correct!)", $time, rdata_o);

      else

        $display("[%0t] << Read data: 0x%h (ERROR! Expected: 0x%h)", $time, rdata_o, expected_data);

    end

  endtask



endmodule

sram_controller_cdc_waves.vcd
$date
	Mon Sep 01 18:35:30 2025
$end
$version
	Icarus Verilog
$end
$timescale
	1ps
$end
$scope module tb_sram_controller $end
$var wire 1 ! ack_o $end
$var wire 16 " rdata_o [15:0] $end
$var wire 8 # sram_addr [7:0] $end
$var wire 1 $ sram_ce $end
$var wire 16 % sram_data [15:0] $end
$var wire 1 & sram_oe $end
$var wire 1 ' sram_we $end
$var reg 8 ( addr_i [7:0] $end
$var reg 1 ) proc_clk $end
$var reg 1 * req_i $end
$var reg 1 + rst_n $end
$var reg 1 , sram_clk $end
$var reg 16 - wdata_i [15:0] $end
$var reg 1 . wr_en_i $end
$scope module dut $end
$var wire 1 ! ack_o $end
$var wire 8 / addr_i [7:0] $end
$var wire 1 0 cmd_fire $end
$var wire 1 1 exec_ready $end
$var wire 1 2 proc_clk $end
$var wire 1 3 req_event $end
$var wire 1 4 req_i $end
$var wire 1 5 rst_n $end
$var wire 8 6 sram_addr_o [7:0] $end
$var wire 1 7 sram_clk $end
$var wire 16 8 sram_data_io [15:0] $end
$var wire 16 9 wdata_i [15:0] $end
$var wire 1 : wr_en_i $end
$var reg 1 ; ack_internal $end
$var reg 1 < ack_p1 $end
$var reg 1 = ack_p2 $end
$var reg 8 > cmd_addr_reg [7:0] $end
$var reg 1 ? cmd_valid_reg $end
$var reg 16 @ cmd_wdata_reg [15:0] $end
$var reg 1 A cmd_wr_en_reg $end
$var reg 4 B exec_current_state [3:0] $end
$var reg 4 C exec_next_state [3:0] $end
$var reg 16 D rdata_o [15:0] $end
$var reg 1 E req_s1 $end
$var reg 1 F req_s2 $end
$var reg 1 G req_s3 $end
$var reg 1 H sram_ce_o $end
$var reg 1 I sram_oe_o $end
$var reg 1 J sram_we_o $end
$upscope $end
$scope module sram_inst $end
$var wire 1 7 clk $end
$var wire 1 5 rst_n $end
$var wire 8 K sram_addr_i [7:0] $end
$var wire 1 $ sram_ce_i $end
$var wire 16 L sram_data_io [15:0] $end
$var wire 1 & sram_oe_i $end
$var wire 1 ' sram_we_i $end
$upscope $end
$scope task read_mem $end
$var reg 8 M address [7:0] $end
$var reg 16 N expected_data [15:0] $end
$upscope $end
$scope task write_mem $end
$var reg 8 O address [7:0] $end
$var reg 16 P data [15:0] $end
$upscope $end
$upscope $end
$enddefinitions $end
#0
$dumpvars
bx P
bx O
bx N
bx M
bz L
bx K
0J
0I
0H
0G
0F
0E
b0 D
b1 C
b1 B
xA
bx @
0?
bx >
0=
0<
0;
x:
bx 9
bz 8
07
bx 6
05
04
03
02
11
00
bx /
x.
bx -
0,
0+
0*
0)
bx (
0'
0&
bz %
0$
bx #
b0 "
0!
$end
#3000
1)
12
#5000
1,
17
#6000
0)
02
#9000
1)
12
#10000
0,
07
#12000
0)
02
#15000
1)
12
1,
17
#18000
0)
02
#20000
0,
07
1+
15
#21000
1)
12
#24000
0)
02
#25000
1,
17
#27000
1)
12
#30000
0)
02
0,
07
#33000
1)
12
#35000
1,
17
#36000
0)
02
#39000
1)
12
#40000
0,
07
#42000
0)
02
#45000
1)
12
1,
17
#48000
0)
02
#50000
0,
07
#51000
1)
12
#54000
0)
02
#55000
1,
17
#57000
1)
12
#60000
0)
02
0,
07
b1011111011101111 P
b10100101 O
#63000
b1011111011101111 -
b1011111011101111 9
b10100101 (
b10100101 /
1.
1:
1*
14
1)
12
#65000
1E
1,
17
#66000
0)
02
#69000
1)
12
#70000
0,
07
#72000
0)
02
#75000
13
1F
1)
12
1,
17
#78000
0)
02
#80000
0,
07
#81000
1)
12
#84000
0)
02
#85000
b100 C
03
10
1?
1A
b1011111011101111 @
b10100101 >
b10100101 #
b10100101 6
b10100101 K
1G
1,
17
#87000
1)
12
#90000
0)
02
0,
07
#93000
1)
12
#95000
b1 C
1;
1J
1'
1H
1$
00
b1011111011101111 %
b1011111011101111 8
b1011111011101111 L
0?
b100 B
01
1,
17
#96000
0)
02
#99000
1<
1)
12
#100000
0,
07
#102000
0)
02
#105000
0J
0'
0H
0$
0;
bz %
bz 8
bz L
1=
1!
b1 B
11
1)
12
1,
17
#108000
0)
02
#110000
0,
07
#111000
0<
0*
04
1)
12
#114000
0)
02
#115000
0E
1,
17
#117000
0=
0!
1)
12
#120000
0)
02
0,
07
#123000
b1111101011001110 -
b1111101011001110 9
b10000 (
b10000 /
1*
14
1)
12
#125000
1E
0F
1,
17
#126000
0)
02
#129000
1)
12
#130000
0,
07
#132000
0)
02
#135000
13
1F
0G
1)
12
1,
17
#138000
0)
02
#140000
0,
07
#141000
0*
04
1)
12
#144000
0)
02
#145000
b100 C
03
10
1?
b1111101011001110 @
b10000 >
b10000 #
b10000 6
b10000 K
0E
1G
1,
17
#147000
1)
12
#150000
0)
02
0,
07
#153000
b10100101 (
b10100101 /
0.
0:
1*
14
1)
12
#155000
b1 C
1;
1J
1'
1H
1$
00
b1111101011001110 %
b1111101011001110 8
b1111101011001110 L
1E
0F
0?
b100 B
01
1,
17
#156000
0)
02
#159000
1<
1)
12
#160000
0,
07
#162000
0)
02
#165000
0J
0'
0H
0$
0;
bz %
bz 8
bz L
13
1=
1!
b1 B
11
1F
0G
1)
12
1,
17
#168000
0)
02
#170000
0,
07
#171000
0<
0*
04
1)
12
#174000
0)
02
#175000
03
b1000 C
10
0E
1G
1?
0A
b10100101 >
b10100101 #
b10100101 6
b10100101 K
1,
17
#177000
0=
0!
1)
12
#180000
0)
02
0,
07
#183000
1)
12
#185000
b1011111011101111 %
b1011111011101111 8
b1011111011101111 L
b1001 C
1I
1&
1H
1$
00
b1000 B
01
0?
0F
1,
17
#186000
0)
02
#189000
1)
12
#190000
0,
07
#192000
0)
02
#195000
b1 C
1;
1I
1&
1H
1$
0G
b1001 B
1)
12
1,
17
#198000
0)
02
#200000
0,
07
#201000
1<
1)
12
#204000
0)
02
#205000
bz %
bz 8
bz L
0I
0&
0H
0$
0;
b1011111011101111 D
b1011111011101111 "
b1 B
11
1,
17
#207000
0<
1=
1!
1)
12
#210000
0)
02
0,
07
#213000
0=
0!
1)
12
