sram_model.v
/*
 * Module: sram_model
 * Description:
 * A behavioral model for a simple synchronous SRAM chip. It includes a reset
 * and has correctly named ports to interface with the controller and testbench.
 * This is the stable, working version for the SRAM-only project.
 */
module sram_model #(
    parameter DATA_WIDTH = 16,
    parameter ADDR_WIDTH = 8
)(
    input                       clk,
    input                       rst_n,
    inout  [DATA_WIDTH-1:0]     sram_data_io,
    input  [ADDR_WIDTH-1:0]     sram_addr_i,
    input                       sram_ce_i,
    input                       sram_we_i,
    input                       sram_oe_i
);

    // Internal memory array
    reg [DATA_WIDTH-1:0] memory [0:(1<<ADDR_WIDTH)-1];
    
    // On the positive clock edge, perform writes
    always @(posedge clk or negedge rst_n) begin
        if (!rst_n) begin
            // On reset, do nothing to the memory contents.
        end else begin
            if (sram_ce_i && sram_we_i && !sram_oe_i) begin
                memory[sram_addr_i] <= sram_data_io;
            end
        end
    end

    // Combinational logic to drive the data bus during a read
    assign sram_data_io = (sram_ce_i && !sram_we_i && sram_oe_i) ? memory[sram_addr_i] : {DATA_WIDTH{1'bz}};

endmodule

sram_controller.v
/*
 * Module: sram_controller (Final, Robust CDC Version with FSM Race Fix)
 */
module sram_controller #(
    parameter ADDR_WIDTH = 8,
    parameter DATA_WIDTH = 16
)(
    // Processor-side Interface (on proc_clk)
    input                       proc_clk,
    input                       req_i,
    input                       wr_en_i,
    input      [ADDR_WIDTH-1:0] addr_i,
    input      [DATA_WIDTH-1:0] wdata_i,
    output                      ack_o,

    // SRAM-side Interface (on sram_clk)
    input                       sram_clk,
    input                       rst_n,
    output reg [DATA_WIDTH-1:0] rdata_o,
    output reg [ADDR_WIDTH-1:0] sram_addr_o,
    inout      [DATA_WIDTH-1:0] sram_data_io,
    output reg                  sram_ce_o,
    output reg                  sram_we_o,
    output reg                  sram_oe_o
);

    // FINAL FIX: Added DECODE state to FSM
    localparam IDLE=4'b0001, DECODE=4'b0010, WRITE=4'b0100, READ_SETUP=4'b1000, READ_CAPTURE=4'b1001;
    
    reg [3:0] current_state, next_state;

    // Internal registers for latched command
    reg [ADDR_WIDTH-1:0] addr_reg;
    reg [DATA_WIDTH-1:0] wdata_reg;
    reg wr_en_reg;
    reg ack_internal;

    // CDC: Synchronize the request signal ONLY
    reg req_s1, req_s2, req_s3;
    always @(posedge sram_clk or negedge rst_n) begin
        if (!rst_n) {req_s1, req_s2, req_s3} <= 3'b0;
        else        {req_s1, req_s2, req_s3} <= {req_i, req_s1, req_s2};
    end
    
    wire req_event = req_s2 & ~req_s3;

    // CDC: Synchronize the ack signal back
    reg ack_p1, ack_p2;
    always @(posedge proc_clk or negedge rst_n) begin
        if (!rst_n) {ack_p1, ack_p2} <= 2'b0;
        else        {ack_p1, ack_p2} <= {ack_internal, ack_p1};
    end
    assign ack_o = ack_p2;

    // Core FSM Sequential Logic (runs on sram_clk)
    always @(posedge sram_clk or negedge rst_n) begin
        if (!rst_n) begin
            current_state <= IDLE;
            rdata_o       <= 0;
        end else begin
            current_state <= next_state;
            if (current_state == IDLE && req_event) begin
                addr_reg  <= addr_i;
                wdata_reg <= wdata_i;
                wr_en_reg <= wr_en_i;
            end
            
            if (current_state == READ_CAPTURE) begin
                rdata_o <= sram_data_io;
            end
        end
    end

    // Core FSM Combinational Logic (runs on sram_clk)
    always @(*) begin
        next_state   = current_state;
        ack_internal = 1'b0;
        sram_addr_o  = addr_reg;
        sram_ce_o    = 1'b0;
        sram_we_o    = 1'b0;
        sram_oe_o    = 1'b0;
        
        case (current_state)
            IDLE: begin
                if (req_event) begin
                    next_state = DECODE;
                end
            end
            // FINAL FIX: Added DECODE state to safely check the latched command
            DECODE: begin
                next_state = wr_en_reg ? WRITE : READ_SETUP;
            end
            WRITE: begin
                sram_ce_o    = 1'b1;
                sram_we_o    = 1'b1;
                ack_internal = 1'b1;
                next_state   = IDLE;
            end
            READ_SETUP: begin
                sram_ce_o  = 1'b1;
                sram_oe_o  = 1'b1;
                next_state = READ_CAPTURE;
            end
            READ_CAPTURE: begin
                sram_ce_o    = 1'b1;
                sram_oe_o    = 1'b1;
                ack_internal = 1'b1;
                next_state   = IDLE;
            end
            default: next_state = IDLE;
        endcase
    end
    
    assign sram_data_io = (current_state == WRITE) ? wdata_reg : {DATA_WIDTH{1'bz}};
endmodule

tb_sram_controller.v
/*
 * Module: tb_sram_controller (With Debug Probes)
 */
`timescale 1ns/1ps

module tb_sram_controller;
    // Parameters and signals
    localparam ADDR_WIDTH = 8;
    localparam DATA_WIDTH = 16;
    localparam SRAM_CLK_PERIOD = 10;
    localparam PROC_CLK_PERIOD = 7;
    reg sram_clk, proc_clk, rst_n, req_i, wr_en_i;
    reg [ADDR_WIDTH-1:0] addr_i;
    reg [DATA_WIDTH-1:0] wdata_i;
    wire ack_o;
    wire [DATA_WIDTH-1:0] rdata_o;
    wire [ADDR_WIDTH-1:0] sram_addr;
    wire [DATA_WIDTH-1:0] sram_data;
    wire sram_ce, sram_we, sram_oe;
    
    // Instantiations
    sram_controller #(.ADDR_WIDTH(ADDR_WIDTH), .DATA_WIDTH(DATA_WIDTH)) dut (.proc_clk(proc_clk), .sram_clk(sram_clk), .rst_n(rst_n), .req_i(req_i), .wr_en_i(wr_en_i), .addr_i(addr_i), .wdata_i(wdata_i), .ack_o(ack_o), .rdata_o(rdata_o), .sram_addr_o(sram_addr), .sram_data_io(sram_data), .sram_ce_o(sram_ce), .sram_we_o(sram_we), .sram_oe_o(sram_oe));
    sram_model #(.ADDR_WIDTH(ADDR_WIDTH), .DATA_WIDTH(DATA_WIDTH)) sram_inst (.clk(sram_clk), .rst_n(rst_n), .sram_addr_i(sram_addr), .sram_data_io(sram_data), .sram_ce_i(sram_ce), .sram_we_i(sram_we), .sram_oe_i(sram_oe));

    // Clocks and Test Sequence
    initial begin sram_clk = 0; forever #(SRAM_CLK_PERIOD/2) sram_clk = ~sram_clk; end
    initial begin proc_clk = 0; forever #(PROC_CLK_PERIOD/2) proc_clk = ~proc_clk; end
    initial begin
        $dumpfile("sram_controller_cdc_waves.vcd");
        $dumpvars(0, tb_sram_controller);
        rst_n = 0; req_i = 0; #20; rst_n = 1; #40;
        $display("----------------------------------------");
        $display("Starting CDC Simulation...");
        write_mem(8'h10, 16'hFACE);
        write_mem(8'hA5, 16'hBEEF);
        read_mem(8'h10, 16'hFACE);
        read_mem(8'hA5, 16'hBEEF);
        $display("----------------------------------------");
        $display("Simulation Finished.");
        $finish;
    end

    // Write task
    task write_mem(input [ADDR_WIDTH-1:0] address, input [DATA_WIDTH-1:0] data);
        begin
            $display("[%0t] >> Writing 0x%h to address 0x%h", $time, data, address);
            @(posedge proc_clk);
            req_i <= 1; wr_en_i <= 1; addr_i <= address; wdata_i <= data;
            while(!ack_o) @(posedge proc_clk);
            req_i <= 0;
            $display("[%0t] << Controller acknowledged the write request.", $time);
            @(posedge proc_clk);
        end
    endtask

    // Read task with debug statements
    task read_mem(input [ADDR_WIDTH-1:0] address, input [DATA_WIDTH-1:0] expected_data);
        begin
            $display("[%0t] >> Reading from address 0x%h", $time, address);
            @(posedge proc_clk);
            req_i <= 1; wr_en_i <= 0; addr_i <= address;
            
            // DEBUG: Show when the ack is received
            while(!ack_o) @(posedge proc_clk);
            $display("[%0t] TB-PROC-CLK: Ack received. Sampling data on next edge.", $time);
            
            req_i <= 0;
            @(posedge proc_clk);

            // DEBUG: Show what data is being sampled
            $display("[%0t] TB-PROC-CLK: Sampling rdata_o, value is %h", $time, rdata_o);
            if (rdata_o == expected_data)
                $display("[%0t] << Read data: 0x%h (Correct!)", $time, rdata_o);
            else
                $display("[%0t] << Read data: 0x%h (ERROR! Expected: 0x%h)", $time, rdata_o, expected_data);
        end
    endtask
endmodule

sram_controller_cdc_waves.vcd
$date
	Mon Sep 01 12:26:43 2025
$end
$version
	Icarus Verilog
$end
$timescale
	1ps
$end
$scope module tb_sram_controller $end
$var wire 1 ! ack_o $end
$var wire 16 " rdata_o [15:0] $end
$var wire 8 # sram_addr [7:0] $end
$var wire 1 $ sram_ce $end
$var wire 16 % sram_data [15:0] $end
$var wire 1 & sram_oe $end
$var wire 1 ' sram_we $end
$var reg 8 ( addr_i [7:0] $end
$var reg 1 ) proc_clk $end
$var reg 1 * req_i $end
$var reg 1 + rst_n $end
$var reg 1 , sram_clk $end
$var reg 16 - wdata_i [15:0] $end
$var reg 1 . wr_en_i $end
$scope module dut $end
$var wire 1 ! ack_o $end
$var wire 8 / addr_i [7:0] $end
$var wire 1 0 proc_clk $end
$var wire 1 1 req_event $end
$var wire 1 2 req_i $end
$var wire 1 3 rst_n $end
$var wire 1 4 sram_clk $end
$var wire 16 5 sram_data_io [15:0] $end
$var wire 16 6 wdata_i [15:0] $end
$var wire 1 7 wr_en_i $end
$var reg 1 8 ack_internal $end
$var reg 1 9 ack_p1 $end
$var reg 1 : ack_p2 $end
$var reg 8 ; addr_reg [7:0] $end
$var reg 4 < current_state [3:0] $end
$var reg 4 = next_state [3:0] $end
$var reg 16 > rdata_o [15:0] $end
$var reg 1 ? req_s1 $end
$var reg 1 @ req_s2 $end
$var reg 1 A req_s3 $end
$var reg 8 B sram_addr_o [7:0] $end
$var reg 1 C sram_ce_o $end
$var reg 1 D sram_oe_o $end
$var reg 1 E sram_we_o $end
$var reg 16 F wdata_reg [15:0] $end
$var reg 1 G wr_en_reg $end
$upscope $end
$scope module sram_inst $end
$var wire 1 4 clk $end
$var wire 1 3 rst_n $end
$var wire 8 H sram_addr_i [7:0] $end
$var wire 1 $ sram_ce_i $end
$var wire 16 I sram_data_io [15:0] $end
$var wire 1 & sram_oe_i $end
$var wire 1 ' sram_we_i $end
$upscope $end
$scope task read_mem $end
$var reg 8 J address [7:0] $end
$var reg 16 K expected_data [15:0] $end
$upscope $end
$scope task write_mem $end
$var reg 8 L address [7:0] $end
$var reg 16 M data [15:0] $end
$upscope $end
$upscope $end
$enddefinitions $end
#0
$dumpvars
bx M
bx L
bx K
bx J
bz I
bx H
xG
bx F
0E
0D
0C
bx B
0A
0@
0?
b0 >
b1 =
b1 <
bx ;
0:
09
08
x7
bx 6
bz 5
04
03
02
01
00
bx /
x.
bx -
0,
0+
0*
0)
bx (
0'
0&
bz %
0$
bx #
b0 "
0!
$end
#3000
1)
10
#5000
1,
14
#6000
0)
00
#9000
1)
10
#10000
0,
04
#12000
0)
00
#15000
1)
10
1,
14
#18000
0)
00
#20000
0,
04
1+
13
#21000
1)
10
#24000
0)
00
#25000
1,
14
#27000
1)
10
#30000
0)
00
0,
04
#33000
1)
10
#35000
1,
14
#36000
0)
00
#39000
1)
10
#40000
0,
04
#42000
0)
00
#45000
1)
10
1,
14
#48000
0)
00
#50000
0,
04
#51000
1)
10
#54000
0)
00
#55000
1,
14
#57000
1)
10
#60000
0)
00
0,
04
b1111101011001110 M
b10000 L
#63000
b1111101011001110 -
b1111101011001110 6
b10000 (
b10000 /
1.
17
1*
12
1)
10
#65000
1?
1,
14
#66000
0)
00
#69000
1)
10
#70000
0,
04
#72000
0)
00
#75000
b10 =
11
1@
1)
10
1,
14
#78000
0)
00
#80000
0,
04
#81000
1)
10
#84000
0)
00
#85000
01
b100 =
b10000 B
b10000 #
b10000 H
1G
b1111101011001110 F
b10000 ;
b10 <
1A
1,
14
#87000
1)
10
#90000
0)
00
0,
04
#93000
1)
10
#95000
b1 =
18
1E
1'
1C
1$
b1111101011001110 %
b1111101011001110 5
b1111101011001110 I
b100 <
1,
14
#96000
0)
00
#99000
19
1)
10
#100000
0,
04
#102000
0)
00
#105000
0E
0'
0C
0$
08
bz %
bz 5
bz I
1:
1!
b1 <
1)
10
1,
14
#108000
0)
00
#110000
0,
04
#111000
09
0*
02
1)
10
#114000
0)
00
#115000
0?
1,
14
#117000
0:
0!
b1011111011101111 M
b10100101 L
1)
10
#120000
0)
00
0,
04
#123000
b1011111011101111 -
b1011111011101111 6
b10100101 (
b10100101 /
1*
12
1)
10
#125000
1?
0@
1,
14
#126000
0)
00
#129000
1)
10
#130000
0,
04
#132000
0)
00
#135000
b10 =
11
1@
0A
1)
10
1,
14
#138000
0)
00
#140000
0,
04
#141000
1)
10
#144000
0)
00
#145000
01
b100 =
b10100101 B
b10100101 #
b10100101 H
b1011111011101111 F
b10100101 ;
b10 <
1A
1,
14
#147000
1)
10
#150000
0)
00
0,
04
#153000
1)
10
#155000
b1 =
18
1E
1'
1C
1$
b1011111011101111 %
b1011111011101111 5
b1011111011101111 I
b100 <
1,
14
#156000
0)
00
#159000
19
1)
10
#160000
0,
04
#162000
0)
00
#165000
0E
0'
0C
0$
08
bz %
bz 5
bz I
1:
1!
b1 <
1)
10
1,
14
#168000
0)
00
#170000
0,
04
#171000
09
0*
02
1)
10
#174000
0)
00
#175000
0?
1,
14
#177000
0:
0!
b1111101011001110 K
b10000 J
1)
10
#180000
0)
00
0,
04
#183000
b10000 (
b10000 /
0.
07
1*
12
1)
10
#185000
1?
0@
1,
14
#186000
0)
00
#189000
1)
10
#190000
0,
04
#192000
0)
00
#195000
b10 =
11
1@
0A
1)
10
1,
14
#198000
0)
00
#200000
0,
04
#201000
1)
10
#204000
0)
00
#205000
01
b1000 =
b10000 B
b10000 #
b10000 H
0G
b10000 ;
b10 <
1A
1,
14
#207000
1)
10
#210000
0)
00
0,
04
#213000
1)
10
#215000
b1111101011001110 %
b1111101011001110 5
b1111101011001110 I
b1001 =
1D
1&
1C
1$
b1000 <
1,
14
#216000
0)
00
#219000
1)
10
#220000
0,
04
#222000
0)
00
#225000
b1 =
18
1D
1&
1C
1$
b1001 <
1)
10
1,
14
#228000
0)
00
#230000
0,
04
#231000
19
1)
10
#234000
0)
00
#235000
bz %
bz 5
bz I
0D
0&
0C
0$
08
b1111101011001110 >
b1111101011001110 "
b1 <
1,
14
#237000
09
1:
1!
1)
10
#240000
0)
00
0,
04
#243000
0:
0!
0*
02
1)
10
#245000
0?
1,
14
#246000
0)
00
#249000
b1011111011101111 K
b10100101 J
1)
10
#250000
0,
04
#252000
0)
00
#255000
b10100101 (
b10100101 /
1*
12
0@
1)
10
1,
14
#258000
0)
00
#260000
0,
04
#261000
1)
10
#264000
0)
00
#265000
1?
0A
1,
14
#267000
1)
10
#270000
0)
00
0,
04
#273000
1)
10
#275000
b10 =
11
1@
1,
14
#276000
0)
00
#279000
1)
10
#280000
0,
04
#282000
0)
00
#285000
01
b1000 =
b10100101 B
b10100101 #
b10100101 H
b10100101 ;
b10 <
1A
1)
10
1,
14
#288000
0)
00
#290000
0,
04
#291000
1)
10
#294000
0)
00
#295000
b1011111011101111 %
b1011111011101111 5
b1011111011101111 I
b1001 =
1D
1&
1C
1$
b1000 <
1,
14
#297000
1)
10
#300000
0)
00
0,
04
#303000
1)
10
#305000
b1 =
18
1D
1&
1C
1$
b1001 <
1,
14
#306000
0)
00
#309000
19
1)
10
#310000
0,
04
#312000
0)
00
#315000
bz %
bz 5
bz I
0D
0&
0C
0$
08
1:
1!
b1011111011101111 >
b1011111011101111 "
b1 <
1)
10
1,
14
#318000
0)
00
#320000
0,
04
#321000
09
0*
02
1)
10
#324000
0)
00
#325000
0?
1,
14
#327000
0:
0!
1)
10
